{
  "main": {
    "id": "839ae8104bec5df5",
    "type": "split",
    "children": [
      {
        "id": "335f783ec7abfc90",
        "type": "tabs",
        "children": [
          {
            "id": "64796f0e757bf721",
            "type": "leaf",
            "state": {
              "type": "markdown",
              "state": {
                "file": "tweet/progress/index.en.md",
                "mode": "source",
                "source": false
              }
            }
          }
        ]
      }
    ],
    "direction": "vertical"
  },
  "left": {
    "id": "fee0dc54f8c509a5",
    "type": "split",
    "children": [
      {
        "id": "c3b3a40021a3aecf",
        "type": "tabs",
        "children": [
          {
            "id": "7401d3e33610c64f",
            "type": "leaf",
            "state": {
              "type": "file-explorer",
              "state": {
                "sortOrder": "alphabetical"
              }
            }
          },
          {
            "id": "0cf877b798d7d295",
            "type": "leaf",
            "state": {
              "type": "search",
              "state": {
                "query": "",
                "matchingCase": false,
                "explainSearch": false,
                "collapseAll": false,
                "extraContext": false,
                "sortOrder": "alphabetical"
              }
            }
          },
          {
            "id": "4994f99d7ee4c908",
            "type": "leaf",
            "state": {
              "type": "bookmarks",
              "state": {}
            }
          }
        ]
      }
    ],
    "direction": "horizontal",
    "width": 300
  },
  "right": {
    "id": "e6fc1bc5a9f0fa51",
    "type": "split",
    "children": [
      {
        "id": "4cbd1af5af2e84a5",
        "type": "tabs",
        "children": [
          {
            "id": "7648552c9ef380c8",
            "type": "leaf",
            "state": {
              "type": "backlink",
              "state": {
                "file": "tweet/progress/index.en.md",
                "collapseAll": false,
                "extraContext": false,
                "sortOrder": "alphabetical",
                "showSearch": false,
                "searchQuery": "",
                "backlinkCollapsed": false,
                "unlinkedCollapsed": true
              }
            }
          },
          {
            "id": "9ad2e4e4aa8dc58f",
            "type": "leaf",
            "state": {
              "type": "outgoing-link",
              "state": {
                "file": "tweet/progress/index.en.md",
                "linksCollapsed": false,
                "unlinkedCollapsed": true
              }
            }
          },
          {
            "id": "bf88764a060dbb40",
            "type": "leaf",
            "state": {
              "type": "tag",
              "state": {
                "sortOrder": "frequency",
                "useHierarchy": true
              }
            }
          },
          {
            "id": "2ce2f008c6e9d84f",
            "type": "leaf",
            "state": {
              "type": "outline",
              "state": {
                "file": "tweet/progress/index.en.md"
              }
            }
          }
        ]
      }
    ],
    "direction": "horizontal",
    "width": 300,
    "collapsed": true
  },
  "left-ribbon": {
    "hiddenItems": {
      "switcher:打开快速切换": false,
      "graph:查看关系图谱": false,
      "canvas:新建白板": false,
      "daily-notes:打开/创建今天的日记": false,
      "templates:插入模板": false,
      "command-palette:打开命令面板": false
    }
  },
  "active": "64796f0e757bf721",
  "lastOpenFiles": [
    "tweet/progress/index.tok.md",
    "tweet/productivity-tools/index.tok.md",
    "tweet/productivity-tools/index.zh.md",
    "tweet/productivity-tools/index.en.md",
    "tweet/joplin-vim-mode/index.tok.md",
    "posts/instant-messaging.en.md",
    "posts/instant-messaging.md",
    "posts/diary.zh.md",
    "posts/diary.en.md",
    "posts/_index.tok.md",
    "posts/_index.en.md",
    "posts/_index.md",
    "tweet/winter/index.zh.md",
    "tweet/winter/index.tok.md",
    "tweet/winter/index.en.md",
    "tweet/easier-publish/index.en.md",
    "tweet/easier-publish/index.tok.md",
    "tweet/easier-publish/index.zh.md",
    "tweet/joplin-vim-mode/index.en.md",
    "tweet/joplin-vim-mode/index.zh.md",
    "_index.tok.md",
    "_index.en.md",
    "tweet/better-search-engine/index.tok.md",
    "tweet/better-search-engine/index.en.md",
    "_index.zh.md",
    "gallery/accurate-colour-wheel/index.zh.md",
    "gallery/accurate-colour-wheel/oklch-colour-wheel.png"
  ]
}